[
    {
        "image_index": 96926,
        "color2_name": "--None--",
        "color1_name": "Firebrick",
        "color1_rgb": [
            178,
            34,
            34
        ],
        "question_string": "Does Firebrick have the highest value?",
        "color2_id": -1,
        "color1_id": 34,
        "answer": 1,
        "color2_rgb": [
            -1,
            -1,
            -1
        ],
        "question_id": 11
    },
    {
        "image_index": 15311,
        "color2_name": "--None--",
        "color1_name": "Violet Red",
        "color1_rgb": [
            199,
            21,
            133
        ],
        "question_string": "Is Violet Red the maximum?",
        "color2_id": -1,
        "color1_id": 66,
        "answer": 1,
        "color2_rgb": [
            -1,
            -1,
            -1
        ],
        "question_id": 1
    },
    {
        "image_index": 98884,
        "color2_name": "Lawn Green",
        "color1_name": "Burlywood",
        "color1_rgb": [
            222,
            184,
            135
        ],
        "question_string": "Is Burlywood less than Lawn Green?",
        "color2_id": 47,
        "color1_id": 5,
        "answer": 0,
        "color2_rgb": [
            124,
            252,
            0
        ],
        "question_id": 12
    },
    {
        "image_index": 81266,
        "color2_name": "--None--",
        "color1_name": "Dim Gray",
        "color1_rgb": [
            105,
            105,
            105
        ],
        "question_string": "Does Dim Gray have the highest value?",
        "color2_id": -1,
        "color1_id": 32,
        "answer": 0,
        "color2_rgb": [
            -1,
            -1,
            -1
        ],
        "question_id": 11
    },
    {
        "image_index": 34426,
        "color2_name": "--None--",
        "color1_name": "Dark Salmon",
        "color1_rgb": [
            233,
            150,
            122
        ],
        "question_string": "Is Dark Salmon the minimum?",
        "color2_id": -1,
        "color1_id": 24,
        "answer": 0,
        "color2_rgb": [
            -1,
            -1,
            -1
        ],
        "question_id": 0
    },
    {
        "image_index": 51558,
        "color2_name": "Saddle Brown",
        "color1_name": "Coral",
        "color1_rgb": [
            255,
            127,
            80
        ],
        "question_string": "Is Coral greater than Saddle Brown?",
        "color2_id": 83,
        "color1_id": 9,
        "answer": 0,
        "color2_rgb": [
            139,
            69,
            19
        ],
        "question_id": 3
    },
    {
        "image_index": 80895,
        "color2_name": "--None--",
        "color1_name": "Tan",
        "color1_rgb": [
            210,
            180,
            140
        ],
        "question_string": "Does Tan have the highest value?",
        "color2_id": -1,
        "color1_id": 93,
        "answer": 0,
        "color2_rgb": [
            -1,
            -1,
            -1
        ],
        "question_id": 11
    },
    {
        "image_index": 33773,
        "color2_name": "--None--",
        "color1_name": "Dark Salmon",
        "color1_rgb": [
            233,
            150,
            122
        ],
        "question_string": "Is Dark Salmon the low median?",
        "color2_id": -1,
        "color1_id": 24,
        "answer": 0,
        "color2_rgb": [
            -1,
            -1,
            -1
        ],
        "question_id": 4
    },
    {
        "image_index": 31128,
        "color2_name": "--None--",
        "color1_name": "Medium Aqua",
        "color1_rgb": [
            102,
            205,
            170
        ],
        "question_string": "Is Medium Aqua the low median?",
        "color2_id": -1,
        "color1_id": 58,
        "answer": 0,
        "color2_rgb": [
            -1,
            -1,
            -1
        ],
        "question_id": 4
    },
    {
        "image_index": 49291,
        "color2_name": "--None--",
        "color1_name": "Dodger Blue",
        "color1_rgb": [
            30,
            144,
            255
        ],
        "question_string": "Is Dodger Blue the maximum?",
        "color2_id": -1,
        "color1_id": 33,
        "answer": 0,
        "color2_rgb": [
            -1,
            -1,
            -1
        ],
        "question_id": 1
    },
    {
        "image_index": 33461,
        "color2_name": "Medium Purple",
        "color1_name": "Turquoise",
        "color1_rgb": [
            64,
            224,
            208
        ],
        "question_string": "Is Turquoise greater than Medium Purple?",
        "color2_id": 61,
        "color1_id": 96,
        "answer": 0,
        "color2_rgb": [
            147,
            112,
            219
        ],
        "question_id": 3
    },
    {
        "image_index": 97683,
        "color2_name": "--None--",
        "color1_name": "Web Purple",
        "color1_rgb": [
            127,
            0,
            127
        ],
        "question_string": "Does Web Purple have the lowest value?",
        "color2_id": -1,
        "color1_id": 78,
        "answer": 1,
        "color2_rgb": [
            -1,
            -1,
            -1
        ],
        "question_id": 10
    },
    {
        "image_index": 61574,
        "color2_name": "Cyan",
        "color1_name": "Olive",
        "color1_rgb": [
            128,
            128,
            0
        ],
        "question_string": "Is Olive less than Cyan?",
        "color2_id": 12,
        "color1_id": 69,
        "answer": 1,
        "color2_rgb": [
            0,
            255,
            255
        ],
        "question_id": 12
    },
    {
        "image_index": 10448,
        "color2_name": "--None--",
        "color1_name": "Light Gold",
        "color1_rgb": [
            255,
            215,
            0
        ],
        "question_string": "Is Light Gold the low median?",
        "color2_id": -1,
        "color1_id": 36,
        "answer": 1,
        "color2_rgb": [
            -1,
            -1,
            -1
        ],
        "question_id": 4
    },
    {
        "image_index": 16865,
        "color2_name": "--None--",
        "color1_name": "Orange Red",
        "color1_rgb": [
            255,
            69,
            0
        ],
        "question_string": "Is Orange Red the minimum?",
        "color2_id": -1,
        "color1_id": 72,
        "answer": 0,
        "color2_rgb": [
            -1,
            -1,
            -1
        ],
        "question_id": 0
    },
    {
        "image_index": 15810,
        "color2_name": "--None--",
        "color1_name": "Indian Red",
        "color1_rgb": [
            205,
            92,
            92
        ],
        "question_string": "Is Indian Red the maximum?",
        "color2_id": -1,
        "color1_id": 44,
        "answer": 1,
        "color2_rgb": [
            -1,
            -1,
            -1
        ],
        "question_id": 1
    },
    {
        "image_index": 44558,
        "color2_name": "--None--",
        "color1_name": "Aqua",
        "color1_rgb": [
            127,
            255,
            212
        ],
        "question_string": "Is Aqua the low median?",
        "color2_id": -1,
        "color1_id": 0,
        "answer": 0,
        "color2_rgb": [
            -1,
            -1,
            -1
        ],
        "question_id": 4
    },
    {
        "image_index": 22998,
        "color2_name": "Maroon",
        "color1_name": "Medium Orchid",
        "color1_rgb": [
            186,
            85,
            211
        ],
        "question_string": "Is Medium Orchid less than Maroon?",
        "color2_id": 56,
        "color1_id": 60,
        "answer": 0,
        "color2_rgb": [
            176,
            48,
            96
        ],
        "question_id": 2
    },
    {
        "image_index": 10137,
        "color2_name": "Green Yellow",
        "color1_name": "Crimson",
        "color1_rgb": [
            220,
            20,
            60
        ],
        "question_string": "Is Crimson less than Green Yellow?",
        "color2_id": 42,
        "color1_id": 11,
        "answer": 1,
        "color2_rgb": [
            173,
            255,
            47
        ],
        "question_id": 2
    },
    {
        "image_index": 2604,
        "color2_name": "--None--",
        "color1_name": "Rosy Brown",
        "color1_rgb": [
            188,
            143,
            143
        ],
        "question_string": "Is Rosy Brown the minimum?",
        "color2_id": -1,
        "color1_id": 81,
        "answer": 0,
        "color2_rgb": [
            -1,
            -1,
            -1
        ],
        "question_id": 0
    },
    {
        "image_index": 3483,
        "color2_name": "--None--",
        "color1_name": "Dark Khaki",
        "color1_rgb": [
            189,
            183,
            107
        ],
        "question_string": "Is Dark Khaki the maximum?",
        "color2_id": -1,
        "color1_id": 18,
        "answer": 1,
        "color2_rgb": [
            -1,
            -1,
            -1
        ],
        "question_id": 1
    },
    {
        "image_index": 99536,
        "color2_name": "Dodger Blue",
        "color1_name": "Black",
        "color1_rgb": [
            0,
            0,
            0
        ],
        "question_string": "Does Black intersect Dodger Blue?",
        "color2_id": 33,
        "color1_id": 1,
        "answer": 1,
        "color2_rgb": [
            30,
            144,
            255
        ],
        "question_id": 14
    },
    {
        "image_index": 53800,
        "color2_name": "--None--",
        "color1_name": "Violet Red",
        "color1_rgb": [
            199,
            21,
            133
        ],
        "question_string": "Is Violet Red the minimum?",
        "color2_id": -1,
        "color1_id": 66,
        "answer": 1,
        "color2_rgb": [
            -1,
            -1,
            -1
        ],
        "question_id": 0
    },
    {
        "image_index": 78387,
        "color2_name": "Olive Drab",
        "color1_name": "Web Gray",
        "color1_rgb": [
            128,
            128,
            128
        ],
        "question_string": "Is Web Gray greater than Olive Drab?",
        "color2_id": 70,
        "color1_id": 39,
        "answer": 0,
        "color2_rgb": [
            107,
            142,
            35
        ],
        "question_id": 13
    },
    {
        "image_index": 70355,
        "color2_name": "--None--",
        "color1_name": "Dark Periwinkle",
        "color1_rgb": [
            72,
            61,
            139
        ],
        "question_string": "Is Dark Periwinkle the roughest?",
        "color2_id": -1,
        "color1_id": 26,
        "answer": 0,
        "color2_rgb": [
            -1,
            -1,
            -1
        ],
        "question_id": 9
    },
    {
        "image_index": 86227,
        "color2_name": "Firebrick",
        "color1_name": "Orange",
        "color1_rgb": [
            255,
            165,
            0
        ],
        "question_string": "Is Orange greater than Firebrick?",
        "color2_id": 34,
        "color1_id": 71,
        "answer": 1,
        "color2_rgb": [
            178,
            34,
            34
        ],
        "question_id": 13
    },
    {
        "image_index": 73577,
        "color2_name": "--None--",
        "color1_name": "Blue Violet",
        "color1_rgb": [
            138,
            43,
            226
        ],
        "question_string": "Is Blue Violet the roughest?",
        "color2_id": -1,
        "color1_id": 3,
        "answer": 1,
        "color2_rgb": [
            -1,
            -1,
            -1
        ],
        "question_id": 9
    },
    {
        "image_index": 21272,
        "color2_name": "--None--",
        "color1_name": "Medium Blue",
        "color1_rgb": [
            0,
            0,
            205
        ],
        "question_string": "Is Medium Blue the low median?",
        "color2_id": -1,
        "color1_id": 59,
        "answer": 0,
        "color2_rgb": [
            -1,
            -1,
            -1
        ],
        "question_id": 4
    },
    {
        "image_index": 13202,
        "color2_name": "Medium Aqua",
        "color1_name": "Crimson",
        "color1_rgb": [
            220,
            20,
            60
        ],
        "question_string": "Is Crimson less than Medium Aqua?",
        "color2_id": 58,
        "color1_id": 11,
        "answer": 1,
        "color2_rgb": [
            102,
            205,
            170
        ],
        "question_id": 2
    },
    {
        "image_index": 75499,
        "color2_name": "--None--",
        "color1_name": "Purple",
        "color1_rgb": [
            160,
            32,
            240
        ],
        "question_string": "Does Purple have the maximum area under the curve?",
        "color2_id": -1,
        "color1_id": 77,
        "answer": 1,
        "color2_rgb": [
            -1,
            -1,
            -1
        ],
        "question_id": 7
    },
    {
        "image_index": 88572,
        "color2_name": "--None--",
        "color1_name": "Magenta",
        "color1_rgb": [
            255,
            0,
            255
        ],
        "question_string": "Does Magenta have the minimum area under the curve?",
        "color2_id": -1,
        "color1_id": 55,
        "answer": 1,
        "color2_rgb": [
            -1,
            -1,
            -1
        ],
        "question_id": 6
    },
    {
        "image_index": 14982,
        "color2_name": "--None--",
        "color1_name": "Orange",
        "color1_rgb": [
            255,
            165,
            0
        ],
        "question_string": "Is Orange the high median?",
        "color2_id": -1,
        "color1_id": 71,
        "answer": 0,
        "color2_rgb": [
            -1,
            -1,
            -1
        ],
        "question_id": 5
    },
    {
        "image_index": 95767,
        "color2_name": "--None--",
        "color1_name": "Teal",
        "color1_rgb": [
            0,
            128,
            128
        ],
        "question_string": "Does Teal have the maximum area under the curve?",
        "color2_id": -1,
        "color1_id": 94,
        "answer": 0,
        "color2_rgb": [
            -1,
            -1,
            -1
        ],
        "question_id": 7
    },
    {
        "image_index": 49556,
        "color2_name": "Crimson",
        "color1_name": "Green Yellow",
        "color1_rgb": [
            173,
            255,
            47
        ],
        "question_string": "Is Green Yellow less than Crimson?",
        "color2_id": 11,
        "color1_id": 42,
        "answer": 1,
        "color2_rgb": [
            220,
            20,
            60
        ],
        "question_id": 2
    },
    {
        "image_index": 63661,
        "color2_name": "--None--",
        "color1_name": "Dark Slate",
        "color1_rgb": [
            47,
            79,
            79
        ],
        "question_string": "Does Dark Slate have the lowest value?",
        "color2_id": -1,
        "color1_id": 27,
        "answer": 0,
        "color2_rgb": [
            -1,
            -1,
            -1
        ],
        "question_id": 10
    },
    {
        "image_index": 489,
        "color2_name": "Light Green",
        "color1_name": "Tomato",
        "color1_rgb": [
            255,
            99,
            71
        ],
        "question_string": "Is Tomato less than Light Green?",
        "color2_id": 49,
        "color1_id": 95,
        "answer": 0,
        "color2_rgb": [
            144,
            238,
            144
        ],
        "question_id": 2
    },
    {
        "image_index": 80654,
        "color2_name": "--None--",
        "color1_name": "Rosy Brown",
        "color1_rgb": [
            188,
            143,
            143
        ],
        "question_string": "Does Rosy Brown have the maximum area under the curve?",
        "color2_id": -1,
        "color1_id": 81,
        "answer": 0,
        "color2_rgb": [
            -1,
            -1,
            -1
        ],
        "question_id": 7
    },
    {
        "image_index": 96745,
        "color2_name": "Sky Blue",
        "color1_name": "Dark Seafoam",
        "color1_rgb": [
            143,
            188,
            143
        ],
        "question_string": "Is Dark Seafoam less than Sky Blue?",
        "color2_id": 88,
        "color1_id": 25,
        "answer": 0,
        "color2_rgb": [
            135,
            206,
            235
        ],
        "question_id": 12
    },
    {
        "image_index": 18956,
        "color2_name": "Orange Red",
        "color1_name": "Dark Green",
        "color1_rgb": [
            0,
            100,
            0
        ],
        "question_string": "Is Dark Green greater than Orange Red?",
        "color2_id": 72,
        "color1_id": 17,
        "answer": 0,
        "color2_rgb": [
            255,
            69,
            0
        ],
        "question_id": 3
    },
    {
        "image_index": 48802,
        "color2_name": "--None--",
        "color1_name": "Coral",
        "color1_rgb": [
            255,
            127,
            80
        ],
        "question_string": "Is Coral the minimum?",
        "color2_id": -1,
        "color1_id": 9,
        "answer": 0,
        "color2_rgb": [
            -1,
            -1,
            -1
        ],
        "question_id": 0
    },
    {
        "image_index": 9624,
        "color2_name": "Dark Slate",
        "color1_name": "Web Purple",
        "color1_rgb": [
            127,
            0,
            127
        ],
        "question_string": "Is Web Purple less than Dark Slate?",
        "color2_id": 27,
        "color1_id": 78,
        "answer": 1,
        "color2_rgb": [
            47,
            79,
            79
        ],
        "question_id": 2
    },
    {
        "image_index": 6269,
        "color2_name": "--None--",
        "color1_name": "Pale Green",
        "color1_rgb": [
            152,
            251,
            152
        ],
        "question_string": "Is Pale Green the maximum?",
        "color2_id": -1,
        "color1_id": 74,
        "answer": 1,
        "color2_rgb": [
            -1,
            -1,
            -1
        ],
        "question_id": 1
    },
    {
        "image_index": 41738,
        "color2_name": "Dim Gray",
        "color1_name": "Yellow Green",
        "color1_rgb": [
            154,
            205,
            50
        ],
        "question_string": "Is Yellow Green less than Dim Gray?",
        "color2_id": 32,
        "color1_id": 99,
        "answer": 0,
        "color2_rgb": [
            105,
            105,
            105
        ],
        "question_id": 2
    },
    {
        "image_index": 13096,
        "color2_name": "--None--",
        "color1_name": "Lime Green",
        "color1_rgb": [
            50,
            205,
            50
        ],
        "question_string": "Is Lime Green the low median?",
        "color2_id": -1,
        "color1_id": 54,
        "answer": 0,
        "color2_rgb": [
            -1,
            -1,
            -1
        ],
        "question_id": 4
    },
    {
        "image_index": 19772,
        "color2_name": "--None--",
        "color1_name": "Gray",
        "color1_rgb": [
            190,
            190,
            190
        ],
        "question_string": "Is Gray the high median?",
        "color2_id": -1,
        "color1_id": 38,
        "answer": 0,
        "color2_rgb": [
            -1,
            -1,
            -1
        ],
        "question_id": 5
    },
    {
        "image_index": 86573,
        "color2_name": "--None--",
        "color1_name": "Forest Green",
        "color1_rgb": [
            34,
            139,
            34
        ],
        "question_string": "Is Forest Green the smoothest?",
        "color2_id": -1,
        "color1_id": 35,
        "answer": 1,
        "color2_rgb": [
            -1,
            -1,
            -1
        ],
        "question_id": 8
    },
    {
        "image_index": 33036,
        "color2_name": "Indigo",
        "color1_name": "Yellow",
        "color1_rgb": [
            255,
            255,
            0
        ],
        "question_string": "Is Yellow greater than Indigo?",
        "color2_id": 45,
        "color1_id": 98,
        "answer": 0,
        "color2_rgb": [
            75,
            0,
            130
        ],
        "question_id": 3
    },
    {
        "image_index": 50080,
        "color2_name": "--None--",
        "color1_name": "Cyan",
        "color1_rgb": [
            0,
            255,
            255
        ],
        "question_string": "Is Cyan the high median?",
        "color2_id": -1,
        "color1_id": 12,
        "answer": 0,
        "color2_rgb": [
            -1,
            -1,
            -1
        ],
        "question_id": 5
    },
    {
        "image_index": 38848,
        "color2_name": "--None--",
        "color1_name": "Light Gold",
        "color1_rgb": [
            255,
            215,
            0
        ],
        "question_string": "Is Light Gold the maximum?",
        "color2_id": -1,
        "color1_id": 36,
        "answer": 1,
        "color2_rgb": [
            -1,
            -1,
            -1
        ],
        "question_id": 1
    },
    {
        "image_index": 81312,
        "color2_name": "--None--",
        "color1_name": "Burlywood",
        "color1_rgb": [
            222,
            184,
            135
        ],
        "question_string": "Does Burlywood have the highest value?",
        "color2_id": -1,
        "color1_id": 5,
        "answer": 0,
        "color2_rgb": [
            -1,
            -1,
            -1
        ],
        "question_id": 11
    }
]